jyflow/__init__.py
jyflow/__main__.py
jyflow/cli.py
jyflow/dataclasses/__init__.py
jyflow/dataclasses/article.py
jyflow/handlers.py
jyflow/parsers/arxiv_parser.py
jyflow/processors/__init__.py
jyflow/processors/embedding.py
jyflow/processors/index_processor.py
jyflow/processors/markdown_processor.py
jyflow/processors/summary_processor.py
jyflow/prompts.toml
jyflow/templates/report.md.j2
jyflow/utils.py
jyflow-0.1.2.dist-info/METADATA
jyflow-0.1.2.dist-info/WHEEL
jyflow-0.1.2.dist-info/entry_points.txt
jyflow-0.1.2.dist-info/RECORD
